gntools/__init__.py
gntools/datasources.py
gntools/definitions.py
gntools/parsers.py
gntools/plans.py
gntools/protocol.py
gntools/common/__init__.py
gntools/common/const.py
gntools/common/geometry.py
gntools/common/i18n.py
gntools-0.9.8.dist-info/LICENSE
gntools-0.9.8.dist-info/METADATA
gntools-0.9.8.dist-info/WHEEL
gntools-0.9.8.dist-info/top_level.txt
gntools-0.9.8.dist-info/RECORD
