Metadata-Version: 2.1
Name: gntools
Version: 0.9.8
Summary: GEONIS toolset for the Geocom Python Framework (Esri ArcGIS).
Home-page: https://github.com/geocom-gis/gntools
Author: Geocom Informatik AG / VertiGIS, Burgdorf, Switzerland
Author-email: github@geocom.ch
License: Apache License 2.0
Project-URL: Source, https://github.com/geocom-gis/gntools
Project-URL: Documentation, https://gntools.readthedocs.io/
Keywords: Geocom,GIS,GEONIS,tools,scripting,framework,spatial,geospatial,geoprocessing,Esri,ArcGIS,ArcPy,VertiGIS
Platform: UNKNOWN
Classifier: Development Status :: 4 - Beta
Classifier: Intended Audience :: Developers
Classifier: Environment :: Other Environment
Classifier: Operating System :: Microsoft :: Windows
Classifier: Topic :: Scientific/Engineering :: GIS
Classifier: License :: OSI Approved :: Apache Software License
Classifier: Programming Language :: Python :: 2.7
Requires-Python: >=2.7.8, <3
Requires-Dist: gpf (>=0.9.4)
Provides-Extra: test
Requires-Dist: pytest ; extra == 'test'
Requires-Dist: pytest-cov ; extra == 'test'
Requires-Dist: mock ; extra == 'test'
Requires-Dist: pytest-mock ; extra == 'test'
